endurance/__init__.py
endurance/__main__.py
endurance-0.1.0.dist-info/LICENSE
endurance-0.1.0.dist-info/METADATA
endurance-0.1.0.dist-info/WHEEL
endurance-0.1.0.dist-info/entry_points.txt
endurance-0.1.0.dist-info/top_level.txt
endurance-0.1.0.dist-info/RECORD
